{"schema_version":1,"quilt_loader":{"group":"com.modrinth","id":"mob_captains_mr","version":"1-v2.1.2","metadata":{"name":"Mob Captains","description":"Rare and strong mobs will spawn, dropping illegally enchanted gear","contributors":{"PuckiSilver":"Owner"},"contact":{"homepage":"https://modrinth.com/datapack/mob-captains","sources":"https://github.com/PuckiSilver/MobCaptains","issues":"https://github.com/PuckiSilver/MobCaptains/issues"},"icon":"mob-captains_pack.png"},"intermediate_mappings":"net.fabricmc:intermediary","depends":[{"id":"quilt_resource_loader","versions":"*","unless":"fabric-resource-loader-v0"}]}}